duckdice_api/__init__.py
duckdice_api/api.py
duckdice_api/client.py
duckdice_api/exceptions.py
duckdice_api/models.py
duckdice_api-1.1.0.dist-info/licenses/LICENSE
duckdice_api-1.1.0.dist-info/METADATA
duckdice_api-1.1.0.dist-info/WHEEL
duckdice_api-1.1.0.dist-info/top_level.txt
duckdice_api-1.1.0.dist-info/RECORD
